sqlalchemy_bigint_id/__init__.py
sqlalchemy_bigint_id/config.py
sqlalchemy_bigint_id/migration.py
sqlalchemy_bigint_id/schema.py
sqlalchemy_bigint_id/types.py
sqlalchemy_bigint_id/utils.py
sqlalchemy_bigint_id/version.py
sqlalchemy_postgres_bigint_id-0.2.0.dist-info/LICENSE
sqlalchemy_postgres_bigint_id-0.2.0.dist-info/METADATA
sqlalchemy_postgres_bigint_id-0.2.0.dist-info/WHEEL
sqlalchemy_postgres_bigint_id-0.2.0.dist-info/top_level.txt
sqlalchemy_postgres_bigint_id-0.2.0.dist-info/RECORD
