Metadata-Version: 2.1
Name: sqlalchemy-postgres-bigint-id
Version: 0.2.0
Summary: SQLAlchemy-Postgres-BigInt-ID
Home-page: https://github.com/alvinchow86/sqlalchemy-postgres-bigint-id
Author: Alvin Chow
Author-email: alvinchow86@gmail.com
License: MIT
Platform: UNKNOWN
Classifier: License :: OSI Approved :: MIT License
Classifier: Programming Language :: Python :: 3
Classifier: Programming Language :: Python :: 3.7
Requires-Python: >=3.6
Requires-Dist: sqlalchemy (>=1.2)
Requires-Dist: python-dateutil (>=2.7)
